ionata_settings/__init__.py
ionata_settings/base.py
ionata_settings/drf.py
ionata_settings/storage.py
ionata_django_settings-0.0.5.dist-info/LICENSE
ionata_django_settings-0.0.5.dist-info/METADATA
ionata_django_settings-0.0.5.dist-info/WHEEL
ionata_django_settings-0.0.5.dist-info/top_level.txt
ionata_django_settings-0.0.5.dist-info/RECORD
